[
  {
    "tipoID": "C",
    "ID": "1095810114",
    "placa_u_documento": "1095810114",
    "nombre_propietario": "N/A",
    "conductor": "JAVIER ANDRES GOMEZ RINCON",
    "correo": "Javigomez9110@gmail.com",
    "resumen": {
      "comparendos": "0",
      "multas": "1",
      "acuerdos_de_pago": "0",
      "total": "$ 573.162"
    },
    "tabla_multa": [
      {
        "tipo": "0000107568  Multa  Fecha resolución: 09/10/2024",
        "notificacion": "No aplica",
        "placa": "SXT074",
        "secretaria": "Medellin",
        "infraccion": "C26...  Proyección pago",
        "estado": "Pendiente de pago",
        "valor": "$ 572.628  Interés $ 534",
        "valor_a_pagar": "$ 573.162  Detalle Pago"
      }
    ]
  }
]